Workbook

Sheet 1. Inputs
A1: AI PRODUCT COST MODEL · Predictive ML Cook Sequencer · 7-Eleven Food Planner
A2: Week 4 deliverable · six tabs · blue = inputs you set · black = formulas
A3: INPUT | B3: VALUE | C3: NOTES / SOURCE
A4: A · INFERENCE INPUTS (what feeds the model each call)
A5: Features per inference call | B5: 50 | C5: Global Features (~10 features) decision_hour — Time of day (0–23) is_weekend — Boolean day_of_week — Categorical (Monday–Sunday) store_type — Categorical (urban/suburban/highway) num_oven_items — Count of items competing oven_capacity — Max items oven can hold (assumed 4) items_queued — Number of items waiting Per-Item Features (~12 features per item) For each item variant (roller grill, pizza 2hr, pizza 4hr, wings 2hr, wings 4hr, hot foods 1hr, hot foods 2hr, hot foods 4hr, bake-in-store): *_demand — Forecast demand *_lcu — Lowest cookable unit *_hold_time — Hold time (1/2/4/24 hrs) *_urgency — 1 / time_remaining *_demand_density — demand / LCU *_time_remaining — Hours until window ends *_margin — Item profit margin (new) *_historical_waste — Historical write-off rate *_equipment_type — Oven vs. roller grill (new) Difference Features (~8 features per pair) diff_demand, diff_urgency, diff_margin, diff_waste diff_hold_time, diff_time_remaining Total per pairwise call: ~50 features
A6: Items ranked per call | B6: 12 | C6: Max items: 12 (roller grill, pizza 2hr/4hr, wings 2hr/4hr, hot foods 1hr/2hr/4hr, bake-in-store)
A7: Inference calls per active user / day | B7: 12 | C7: Decision points every 2 hours × 12 windows/day (24-hour operation)
A8: Active users (stores) — pilot | B8: 50 | C8: Pilot scope: 50 stores; scale tabs model 500 → 13,000
A9: Avg peak hours / store / day | B9: 8 | C9: Peak lunch (10–14) and dinner (16–20) within 24-hour window
A10: B · MODEL HOSTING & SERVING COST
A11: Inference compute cost ($/1,000 calls) | B11: 0.004 | C11: Tabular ML inference on managed endpoint (e.g., AWS SageMaker, Azure ML, GCP Vertex). Scikit-learn / XGBoost latency <50ms. ~$4/M calls. Source: AWS SageMaker pricing, real-time inference, ml.t3.medium
A12: Hosting / endpoint monthly fee ($) | B12: 150 | C12: Always-on managed endpoint: ~$0.20/hr × 730 hrs. Covers all stores; fixed cost amortized across users. Source: AWS SageMaker ml.t3.medium on-demand
A13: API gateway / routing fee ($/1,000 calls) | B13: 0.0035 | C13: REST API calls through gateway (AWS API Gateway: $3.50/M calls). Source: AWS API Gateway pricing 2025
A14: C · MODEL TRAINING & RETRAINING
A15: Initial training compute cost ($) | B15: 200 | C15: One-time: XGBoost/LightGBM on synthesized + pilot data. GPU not required for tabular. Estimated 4 hrs × $50/hr on ml.m5.xlarge. Source: AWS SageMaker training jobs pricing
A16: Retraining frequency (per year) | B16: 4 | C16: Quarterly retraining as labeled outcome data (cook sequence → daypart hit/miss) accumulates from pilot stores
A17: Cost per retraining run ($) | B17: 80 | C17: Incremental retraining on updated labeled data; shorter run than initial. ~2 hrs × $40/hr
A18: Training amortization window (months) | B18: 18 | C18: Spread initial training cost across 18-month product life before next model version
A19: D · INSTRUMENTATION, EVAL & OBSERVABILITY
A20: Override logging storage ($/user/mo) | B20: =0.023*0.006 -> 0.000138 | C20: S3 / GCS storage for override logs (associate accepted/rejected ranking + outcome). ~200KB/store/day × 30 days = 6MB/store/mo = 0.006GB/store/mo. Source: AWS S3 standard storage $0.023 per GB/month (first 50TB)$0.022 per GB/month (next 450TB)$0.021 per GB/month (over 500TB)
A21: Observability platform monthly fee ($) | B21: 40 | C21: Model monitoring: drift detection, accuracy tracking, latency alerts. Source: Arize AI / Fiddler AI starter tier ~$40/mo
A22: Eval — % calls auto-validated vs. daypart outcome | B22: 0.1 | C22: 10% of ranked calls matched back to actual daypart hit/miss outcome label for continuous accuracy tracking
A23: Eval — % outputs human-reviewed (ops spot-check) | B23: 0.01 | C23: 1% of ranking decisions reviewed by ops team for quality assurance
A24: Human review cost per decision ($) | B24: 2 | C24: Ops analyst time: 5 min × $24/hr fully loaded. Higher than LLM eval because reviewer must check actual cook log vs. recommendation
A25: E · FIXED OVERHEAD (amortized)
A26: Cloud egress + misc ($/store/mo) | B26: 0.5 | C26: Data transfer, logging egress, misc cloud overhead per store per month
A27: Feature store / data pipeline monthly fee ($) | B27: 60 | C27: Managed feature store for real-time feature serving (cook time, inventory, daypart urgency). Source: AWS Feature Store serverless tier ~$60/mo fixed
A28: ⚠ KEY DIFFERENCE FROM LLM/RAG MODEL: No token costs. No vector DB. No embedding pipeline. Cost drivers are: inference compute per call (tabular ML, not generative), model hosting endpoint (fixed), retraining cadence (periodic, not continuous), and override instrumentation (the feedback loop IS the product moat).

Sheet 2. Per-call
A1: PER-CALL COST · Computed from Tab 1 inputs
A2: One 'call' = one cook-sequence ranking request from one associate at one store
A3: INPUT | B3: VALUE | C3: NOTES / SOURCE
A4: Inference compute | B4: ='1. Inputs'!B11/1000 -> 4e-06 | C4: Inference cost per call = $per-1K-calls ÷ 1,000
A5: API gateway / routing | B5: ='1. Inputs'!B13/1000 -> 3.5e-06 | C5: API gateway cost per call
A6: Override log storage (per call) | B6: ='1. Inputs'!B20/('1. Inputs'!B8*'1. Inputs'!B7*30) -> 7.6666667e-09 | C6: Monthly storage ÷ (stores × calls/user/day × 30 days)
A7: Eval — auto-validation (amortized) | B7: ='1. Inputs'!B22*('1. Inputs'!B11/1000) -> 4e-07 | C7: % validated × compute cost (outcome matching, not LLM judge)
A8: Eval — human spot-check (avg) | B8: ='1. Inputs'!B23*'1. Inputs'!B24 -> 0.02 | C8: % human-reviewed × $ per review
A9: Cloud egress (per call) | B9: ='1. Inputs'!B26/('1. Inputs'!B7*30) -> 0.0013888889 | C9: Monthly egress per store ÷ calls/day × 30
A10: TOTAL per call | B10: =SUM(B4:B9) -> 0.021396797 | C10: Sum of all per-call cost components
A12: Note: Retraining cost and hosting endpoint are FIXED costs — they do NOT appear here. They are amortized in Tab 3 (Per-User) and fall per user as scale grows (Tab 4).

Sheet 3. Per-user
A1: PER-USER (STORE) COST · Pilot scale: 50 stores
A2: Per-call × calls/store/month + amortized fixed costs across pilot store count
A3: INPUT | B3: VALUE | C3: NOTES / SOURCE
A4: VARIABLE COSTS (scale with calls)
A5: Per-call cost × calls/store/month | B5: ='2. Per-call'!B10*'1. Inputs'!B7*30 -> 7.7028468 | C5: Per-call total × calls/day × 30 days
A6: FIXED COSTS (amortized across pilot stores)
A7: Hosting endpoint amortized | B7: ='1. Inputs'!B12/'1. Inputs'!B8 -> 3 | C7: Fixed monthly endpoint fee ÷ pilot store count
A8: Observability platform amortized | B8: ='1. Inputs'!B21/'1. Inputs'!B8 -> 0.8 | C8: Fixed monitoring fee ÷ pilot stores
A9: Feature store amortized | B9: ='1. Inputs'!B27/'1. Inputs'!B8 -> 1.2 | C9: Fixed data pipeline fee ÷ pilot stores
A10: Retraining cost amortized (per store/mo) | B10: =('1. Inputs'!B15/'1. Inputs'!B17+'1. Inputs'!B16*'1. Inputs'!B18/12)/'1. Inputs'!B8 -> 0.17 | C10: ( Initial training ÷ amort. window + annual retraining/12 ) ÷ pilot stores
A11: TOTAL per store / month | B11: =B5+SUM(B7:B10) -> 12.872847 | C11: Variable + all amortized fixed costs

Sheet 4. Scale curve
A1: COST PER STORE AT FIVE SCALE POINTS · Fixed costs amortize; variable scales linearly with calls
A2: COST COMPONENT | B2: 50 (Pilot) | C2: 500 (Phase 2) | D2: 1,300 (Regional) | E2: 5,000 (Half chain) | F2: 13,000 (Full chain)
A3: Variable: per-call × calls/store/mo | B3: ='2. Per-call'!B10*'1. Inputs'!B7*30 -> 7.7028468 | C3: ='2. Per-call'!B10*'1. Inputs'!B7*30 -> 7.7028468 | D3: ='2. Per-call'!B10*'1. Inputs'!B7*30 -> 7.7028468 | E3: ='2. Per-call'!B10*'1. Inputs'!B7*30 -> 7.7028468 | F3: ='2. Per-call'!B10*'1. Inputs'!B7*30 -> 7.7028468
A4: Fixed: hosting endpoint / stores | B4: ='1. Inputs'!B12/50 -> 3 | C4: ='1. Inputs'!B12/500 -> 0.3 | D4: ='1. Inputs'!B12/1300 -> 0.11538462 | E4: ='1. Inputs'!B12/5000 -> 0.03 | F4: ='1. Inputs'!B12/13000 -> 0.011538462
A5: Fixed: observability / stores | B5: ='1. Inputs'!B21/50 -> 0.8 | C5: ='1. Inputs'!B21/500 -> 0.08 | D5: ='1. Inputs'!B21/1300 -> 0.030769231 | E5: ='1. Inputs'!B21/5000 -> 0.008 | F5: ='1. Inputs'!B21/13000 -> 0.0030769231
A6: Fixed: feature store / stores | B6: ='1. Inputs'!B27/50 -> 1.2 | C6: ='1. Inputs'!B27/500 -> 0.12 | D6: ='1. Inputs'!B27/1300 -> 0.046153846 | E6: ='1. Inputs'!B27/5000 -> 0.012 | F6: ='1. Inputs'!B27/13000 -> 0.0046153846
A7: Fixed: retraining amortized / stores | B7: =('1. Inputs'!B15/'1. Inputs'!B17+'1. Inputs'!B16*'1. Inputs'!B18/12)/50 -> 0.17 | C7: =('1. Inputs'!B15/'1. Inputs'!B17+'1. Inputs'!B16*'1. Inputs'!B18/12)/500 -> 0.017 | D7: =('1. Inputs'!B15/'1. Inputs'!B17+'1. Inputs'!B16*'1. Inputs'!B18/12)/1300 -> 0.0065384615 | E7: =('1. Inputs'!B15/'1. Inputs'!B17+'1. Inputs'!B16*'1. Inputs'!B18/12)/5000 -> 0.0017 | F7: =('1. Inputs'!B15/'1. Inputs'!B17+'1. Inputs'!B16*'1. Inputs'!B18/12)/13000 -> 0.00065384615
A8: TOTAL cost / store / month | B8: =SUM(B3:B7) -> 12.872847 | C8: =SUM(C3:C7) -> 8.2198468 | D8: =SUM(D3:D7) -> 7.9016929 | E8: =SUM(E3:E7) -> 7.7545468 | F8: =SUM(F3:F7) -> 7.7227314
A9: Curve shape | B9: Variable cost dominates at pilot (50 stores). Fixed costs become negligible by full-chain (13,000 stores). Cost per store converges toward variable-only floor. Unlike LLM: no token explosion — compute cost per call is flat and predictable.

Sheet 5. Margin
A1: MARGIN ANALYSIS · Internal tool: margin = write-off savings vs. total cost of ownership
A2: This is an internal 7-Eleven product — no SaaS price. 'Price' = monthly write-off savings per store attributable to the feature. Business case: savings must exceed TCO.
A3: Estimated monthly write-off savings per store ($) | B3: 180 | C3: Assumption: 2 units/hr reduction × 4 peak hrs/day × 30 days × $0.75 avg item cost. Adjust when pilot data available.
A4: METRIC | B4: 50 (Pilot) | C4: 500 | D4: 1,300 | E4: 5,000 | F4: 13,000 (Full chain)
A5: Cost / store / month | B5: ='2. Per-call'!B10*'1. Inputs'!B7*30+'1. Inputs'!B12/50+'1. Inputs'!B21/50+'1. Inputs'!B27/50+('1. Inputs'!B15/'1. Inputs'!B17+'1. Inputs'!B16*'1. Inputs'!B18/12)/50 -> 12.872847 | C5: ='2. Per-call'!B10*'1. Inputs'!B7*30+'1. Inputs'!B12/500+'1. Inputs'!B21/500+'1. Inputs'!B27/500+('1. Inputs'!B15/'1. Inputs'!B17+'1. Inputs'!B16*'1. Inputs'!B18/12)/500 -> 8.2198468 | D5: ='2. Per-call'!B10*'1. Inputs'!B7*30+'1. Inputs'!B12/1300+'1. Inputs'!B21/1300+'1. Inputs'!B27/1300+('1. Inputs'!B15/'1. Inputs'!B17+'1. Inputs'!B16*'1. Inputs'!B18/12)/1300 -> 7.9016929 | E5: ='2. Per-call'!B10*'1. Inputs'!B7*30+'1. Inputs'!B12/5000+'1. Inputs'!B21/5000+'1. Inputs'!B27/5000+('1. Inputs'!B15/'1. Inputs'!B17+'1. Inputs'!B16*'1. Inputs'!B18/12)/5000 -> 7.7545468 | F5: ='2. Per-call'!B10*'1. Inputs'!B7*30+'1. Inputs'!B12/13000+'1. Inputs'!B21/13000+'1. Inputs'!B27/13000+('1. Inputs'!B15/'1. Inputs'!B17+'1. Inputs'!B16*'1. Inputs'!B18/12)/13000 -> 7.7227314
A6: Savings / store / month | B6: =$B$3 -> 180 | C6: =$B$3 -> 180 | D6: =$B$3 -> 180 | E6: =$B$3 -> 180 | F6: =$B$3 -> 180
A7: Net benefit / store / month | B7: =B6-B5 -> 167.12715 | C7: =C6-C5 -> 171.78015 | D7: =D6-D5 -> 172.09831 | E7: =E6-E5 -> 172.24545 | F7: =F6-F5 -> 172.27727
A8: ROI % (savings ÷ cost) | B8: =B6/B5-1 -> 12.982921 | C8: =C6/C5-1 -> 20.898218 | D8: =D6/D5-1 -> 21.779929 | E8: =E6/E5-1 -> 22.212188 | F8: =F6/F5-1 -> 22.307816
A9: Flag if cost > savings | B9: =IF(B5>B6,"⚠ COST EXCEEDS SAVINGS","✓ Positive ROI") -> ✓ Positive ROI | C9: =IF(C5>C6,"⚠ COST EXCEEDS SAVINGS","✓ Positive ROI") -> ✓ Positive ROI | D9: =IF(D5>D6,"⚠ COST EXCEEDS SAVINGS","✓ Positive ROI") -> ✓ Positive ROI | E9: =IF(E5>E6,"⚠ COST EXCEEDS SAVINGS","✓ Positive ROI") -> ✓ Positive ROI | F9: =IF(F5>F6,"⚠ COST EXCEEDS SAVINGS","✓ Positive ROI") -> ✓ Positive ROI

Sheet 6. Sensitivity
A1: SENSITIVITY ANALYSIS · Which input moves cost most? · At 1,300 stores (regional scale)
A2: Halve / double each key input; observe change in cost/store/month. Base = Tab 4 formula at 1,300 stores.
A3: INPUT VARIED | B3: BASE VALUE | C3: HALF VALUE | D3: DOUBLE VALUE | E3: INTERPRETATION
A4: Inference calls per store / day | B4: ='1. Inputs'!B7 -> 12 | C4: =('2. Per-call'!B10*('1. Inputs'!B7/2)*30)+'1. Inputs'!B12/1300+'1. Inputs'!B21/1300+'1. Inputs'!B27/1300+('1. Inputs'!B15/'1. Inputs'!B17+'1. Inputs'!B16*'1. Inputs'!B18/12)/1300 -> 4.0502695 | D4: =('2. Per-call'!B10*('1. Inputs'!B7*2)*30)+'1. Inputs'!B12/1300+'1. Inputs'!B21/1300+'1. Inputs'!B27/1300+('1. Inputs'!B15/'1. Inputs'!B17+'1. Inputs'!B16*'1. Inputs'!B18/12)/1300 -> 15.60454 | E4: Most sensitive variable cost driver. Doubling calls = doubling variable cost. Driven by peak hours and decision frequency.
A5: Inference compute ($/1K calls) | B5: ='1. Inputs'!B11 -> 0.004 | C5: =(('1. Inputs'!B11/2)/1000*'1. Inputs'!B7*30)+'1. Inputs'!B12/1300+'1. Inputs'!B21/1300+'1. Inputs'!B27/1300+('1. Inputs'!B15/'1. Inputs'!B17+'1. Inputs'!B16*'1. Inputs'!B18/12)/1300 -> 0.19956615 | D5: =(('1. Inputs'!B11*2)/1000*'1. Inputs'!B7*30)+'1. Inputs'!B12/1300+'1. Inputs'!B21/1300+'1. Inputs'!B27/1300+('1. Inputs'!B15/'1. Inputs'!B17+'1. Inputs'!B16*'1. Inputs'!B18/12)/1300 -> 0.20172615 | E5: Low sensitivity: tabular ML inference is cheap. Even 2× price barely moves total.
A6: Hosting endpoint monthly fee ($) | B6: ='1. Inputs'!B12 -> 150 | C6: ='2. Per-call'!B10*'1. Inputs'!B7*30+('1. Inputs'!B12/2)/1300+'1. Inputs'!B21/1300+'1. Inputs'!B27/1300+('1. Inputs'!B15/'1. Inputs'!B17+'1. Inputs'!B16*'1. Inputs'!B18/12)/1300 -> 7.8440006 | D6: ='2. Per-call'!B10*'1. Inputs'!B7*30+('1. Inputs'!B12*2)/1300+'1. Inputs'!B21/1300+'1. Inputs'!B27/1300+('1. Inputs'!B15/'1. Inputs'!B17+'1. Inputs'!B16*'1. Inputs'!B18/12)/1300 -> 8.0170775 | E6: Negligible at 1,300 stores — fully amortized. Matters only at pilot scale (50 stores).
A7: Retraining cost per run ($) | B7: ='1. Inputs'!B18 -> 18 | C7: ='2. Per-call'!B10*'1. Inputs'!B7*30+'1. Inputs'!B12/1300+'1. Inputs'!B21/1300+'1. Inputs'!B27/1300+('1. Inputs'!B15/'1. Inputs'!B17+'1. Inputs'!B16*('1. Inputs'!B18/2)/12)/1300 -> 7.8993852 | D7: ='2. Per-call'!B10*'1. Inputs'!B7*30+'1. Inputs'!B12/1300+'1. Inputs'!B21/1300+'1. Inputs'!B27/1300+('1. Inputs'!B15/'1. Inputs'!B17+'1. Inputs'!B16*('1. Inputs'!B18*2)/12)/1300 -> 7.9063083 | E7: Low sensitivity at scale. Retraining is infrequent (quarterly) and amortized across stores.
A8: % human spot-check | B8: ='1. Inputs'!B23 -> 0.01 | C8: =('2. Per-call'!B4+'2. Per-call'!B5+('1. Inputs'!B22*('1. Inputs'!B11/1000))+('1. Inputs'!B23/2)*'1. Inputs'!B24+'2. Per-call'!B6)*'1. Inputs'!B7*30+'1. Inputs'!B12/1300+'1. Inputs'!B21/1300+'1. Inputs'!B27/1300+('1. Inputs'!B15/'1. Inputs'!B17+'1. Inputs'!B16*'1. Inputs'!B18/12)/1300 -> 3.8016929 | D8: =('2. Per-call'!B4+'2. Per-call'!B5+('1. Inputs'!B22*('1. Inputs'!B11/1000))+('1. Inputs'!B23*2)*'1. Inputs'!B24+'2. Per-call'!B6)*'1. Inputs'!B7*30+'1. Inputs'!B12/1300+'1. Inputs'!B21/1300+'1. Inputs'!B27/1300+('1. Inputs'!B15/'1. Inputs'!B17+'1. Inputs'!B16*'1. Inputs'!B18/12)/1300 -> 14.601693 | E8: Human review is expensive per unit. Doubling spot-check rate meaningfully raises cost. Keep at 1% unless quality issues emerge.
A9: KEY TAKEAWAY: Call volume (decisions/day) is the dominant variable cost driver — not compute price. Unlike LLM products, there is no output token explosion risk. The main scale risk is adoption: if stores use the tool more than modeled (>20 decisions/day), variable cost rises proportionally. Fixed costs (hosting, retraining) are negligible at regional/full-chain scale.
